pdf_mcp/__init__.py
pdf_mcp/pdf_tools.py
pdf_mcp/server.py
pdf_mcp/text_image.py
pdf_mcp/utils.py
pdf_mcp_server-0.1.0.dist-info/METADATA
pdf_mcp_server-0.1.0.dist-info/WHEEL
pdf_mcp_server-0.1.0.dist-info/entry_points.txt
pdf_mcp_server-0.1.0.dist-info/licenses/LICENSE
pdf_mcp_server-0.1.0.dist-info/RECORD
