Metadata-Version: 2.4
Name: pdf-mcp-server
Version: 0.1.0
Summary: Model Context Protocol PDF service implemented in Python
Project-URL: Homepage, https://github.com/yourusername/pdf-mcp-server
Project-URL: Repository, https://github.com/yourusername/pdf-mcp-server
Project-URL: Issues, https://github.com/yourusername/pdf-mcp-server/issues
Author-email: Your Name <your.email@example.com>
License: MIT
License-File: LICENSE
Keywords: fastmcp,mcp,model-context-protocol,pdf
Classifier: Development Status :: 4 - Beta
Classifier: Intended Audience :: Developers
Classifier: License :: OSI Approved :: MIT License
Classifier: Programming Language :: Python :: 3
Classifier: Programming Language :: Python :: 3.10
Classifier: Programming Language :: Python :: 3.11
Classifier: Programming Language :: Python :: 3.12
Requires-Python: >=3.10
Requires-Dist: fastmcp
Requires-Dist: pikepdf
Requires-Dist: pillow
Requires-Dist: pymupdf
